barracuda/__init__.py
barracuda/activations.py
barracuda/factory.py
barracuda/functions.py
barracuda/losses.py
barracuda/models.py
barracuda/network.py
barracuda/neurons.py
barracuda/neurontype.py
pybarracuda-0.0.5.dist-info/LICENSE
pybarracuda-0.0.5.dist-info/METADATA
pybarracuda-0.0.5.dist-info/WHEEL
pybarracuda-0.0.5.dist-info/top_level.txt
pybarracuda-0.0.5.dist-info/RECORD
