Metadata-Version: 2.1
Name: pybarracuda
Version: 0.0.5
Summary: high performance deep neural network genetic algorithm library
Home-page: https://github.com/BurhanCabiroglu/Barracuda
Author: Burhan Cabiroglu
Author-email: burhancabiroglu97@gmail.com
License: UNKNOWN
Project-URL: Bug Tracker, https://github.com/BurhanCabiroglu/Barracuda
Platform: UNKNOWN
Classifier: Programming Language :: Python :: 3
Classifier: License :: OSI Approved :: MIT License
Classifier: Operating System :: OS Independent
Requires-Python: >=3.5
Requires-Dist: numpy
